<nodeTypes xmlns:nt="http://www.jcp.org/jcr/nt/1.0" xmlns:mix="http://www.jcp.org/jcr/mix/1.0" xmlns:jcr="http://www.jcp.org/jcr/1.0">

  <nodeType name="exo:forumCategory" isMixin="false" hasOrderableChildNodes="false" primaryItemName="">
    <supertypes>
      <supertype>nt:base</supertype>
    </supertypes>
    <propertyDefinitions> 
        <propertyDefinition name="exo:id" requiredType="String" autoCreated="false" mandatory="false" onParentVersion="COPY" protected="false" multiple="false">
        <valueConstraints/>
      </propertyDefinition>     
      <propertyDefinition name="exo:owner" requiredType="String" autoCreated="false" mandatory="false" onParentVersion="COPY" protected="false" multiple="false">
        <valueConstraints/>
      </propertyDefinition>     
      <propertyDefinition name="exo:path" requiredType="String" autoCreated="false" mandatory="false" onParentVersion="COPY" protected="false" multiple="false">
        <valueConstraints/>
      </propertyDefinition>
      <propertyDefinition name="exo:createdDate" requiredType="Date" autoCreated="false" mandatory="false" onParentVersion="COPY" protected="false" multiple="false">
        <valueConstraints/>
      </propertyDefinition>
      <propertyDefinition name="exo:modifiedBy" requiredType="String" autoCreated="false" mandatory="false" onParentVersion="COPY" protected="false" multiple="false">
        <valueConstraints/>
      </propertyDefinition>
      <propertyDefinition name="exo:name" requiredType="String" autoCreated="false" mandatory="false" onParentVersion="COPY" protected="false" multiple="false">
        <valueConstraints/>
      </propertyDefinition>     
      <propertyDefinition name="exo:modifiedDate" requiredType="Date" autoCreated="false" mandatory="false" onParentVersion="COPY" protected="false" multiple="false">
        <valueConstraints/>
      </propertyDefinition>
      <propertyDefinition name="exo:description" requiredType="String" autoCreated="false" mandatory="false" onParentVersion="COPY" protected="false" multiple="false">
        <valueConstraints/>
      </propertyDefinition>
      <propertyDefinition name="exo:moderators" requiredType="String" autoCreated="false" mandatory="false" onParentVersion="COPY" protected="false" multiple="true">
        <valueConstraints/>
      </propertyDefinition>
      <propertyDefinition name="exo:tempModerators" requiredType="String" autoCreated="false" mandatory="false" onParentVersion="COPY" protected="false" multiple="true">
        <valueConstraints/>
      </propertyDefinition>
      <propertyDefinition name="exo:createTopicRole" requiredType="String" autoCreated="false" mandatory="false" onParentVersion="COPY" protected="false" multiple="true">
        <valueConstraints/>
      </propertyDefinition>
      <propertyDefinition name="exo:poster" requiredType="String" autoCreated="false" mandatory="false" onParentVersion="COPY" protected="false" multiple="true">
        <valueConstraints/>
      </propertyDefinition>
      <propertyDefinition name="exo:viewer" requiredType="String" autoCreated="false" mandatory="false" onParentVersion="COPY" protected="false" multiple="true">
        <valueConstraints/>
      </propertyDefinition>
      <propertyDefinition name="exo:categoryOrder" requiredType="Long" autoCreated="false" mandatory="false" onParentVersion="COPY" protected="false" multiple="false">
        <valueConstraints/>
      </propertyDefinition>
      <propertyDefinition name="exo:userPrivate" requiredType="String" autoCreated="false" mandatory="false" onParentVersion="COPY" protected="false" multiple="true">
        <valueConstraints/>
      </propertyDefinition>
      <propertyDefinition name="exo:forumCount" requiredType="Long" autoCreated="false" mandatory="false" onParentVersion="COPY" protected="false" multiple="false">
        <valueConstraints/>
      </propertyDefinition>
      <propertyDefinition name="exo:includedSpace" requiredType="Boolean" autoCreated="false" mandatory="false" onParentVersion="COPY" protected="false" multiple="false">
        <valueConstraints/>
        <defaultValues>
          <defaultValue>false</defaultValue>
        </defaultValues>
      </propertyDefinition>
    </propertyDefinitions>
    
    <childNodeDefinitions>
      <childNodeDefinition name="*" defaultPrimaryType="exo:forum" autoCreated="false" mandatory="false" onParentVersion="VERSION" protected="false" sameNameSiblings="false">
        <requiredPrimaryTypes>
        <requiredPrimaryType>exo:forum</requiredPrimaryType>
        </requiredPrimaryTypes>
      </childNodeDefinition>
      
      <childNodeDefinition name="*" defaultPrimaryType="exo:forumRSS" autoCreated="false" mandatory="false" onParentVersion="COPY" protected="false" sameNameSiblings="false">
        <requiredPrimaryTypes>
          <requiredPrimaryType>nt:base</requiredPrimaryType>
        </requiredPrimaryTypes>
      </childNodeDefinition>
      
    </childNodeDefinitions>
  </nodeType> 
</nodeTypes>